get_isp/__init__.py
get_isp/helpers/__init__.py
get_isp/helpers/exceltools.py
get_isp/helpers/ispchecker.py
get_isp/main.py
get_isp-0.2.2.dist-info/METADATA
get_isp-0.2.2.dist-info/WHEEL
get_isp-0.2.2.dist-info/entry_points.txt
get_isp-0.2.2.dist-info/RECORD
